mplexaa/__init__.py
mplexaa/indices.py
mplexaa/multiplex_graph.py
mplexaa/utils.py
mplexaa-0.1.2.dist-info/LICENSE
mplexaa-0.1.2.dist-info/METADATA
mplexaa-0.1.2.dist-info/WHEEL
mplexaa-0.1.2.dist-info/top_level.txt
mplexaa-0.1.2.dist-info/RECORD
