Metadata-Version: 2.1
Name: mplexaa
Version: 0.1.2
Summary: A package for computing the Multiplex Adamic-Adar score, a measure of node similarity in multiplex networks.
Home-page: https://github.com/cem-sirin/mplexaa
Author: Cem Sirin
Author-email: sirincem1@gmail.com
License-File: LICENSE
Requires-Dist: pandas
Requires-Dist: networkx
Requires-Dist: numpy
Requires-Dist: scipy
